setup.cfg
setup.py
ansible_role/__init__.py
ansible_role/console.py
ansible_role/version.py
ansible_role.egg-info/PKG-INFO
ansible_role.egg-info/SOURCES.txt
ansible_role.egg-info/dependency_links.txt
ansible_role.egg-info/entry_points.txt
ansible_role.egg-info/not-zip-safe
ansible_role.egg-info/requires.txt
ansible_role.egg-info/top_level.txt